django_login_required-0.2.dist-info/METADATA
django_login_required-0.2.dist-info/RECORD
django_login_required-0.2.dist-info/WHEEL
django_login_required-0.2.dist-info/top_level.txt
login_required/__init__.py
login_required/middleware.py
